sonyflake_turbo.abi3.so
sonyflake_turbo-0.1.0.dist-info/LICENSE
sonyflake_turbo-0.1.0.dist-info/METADATA
sonyflake_turbo-0.1.0.dist-info/WHEEL
sonyflake_turbo-0.1.0.dist-info/top_level.txt
sonyflake_turbo-0.1.0.dist-info/RECORD
