Metadata-Version: 2.1
Name: sonyflake-turbo
Version: 0.1.0
Summary: A Sonyflake implementation optimized for extreme usages.
Author-email: Anatolii Aniskovych <zipfile.d@protonmail.com>
License: BSD-2-Clause
Project-URL: Source, https://github.com/ZipFile/python-sonyflake-turbo
Keywords: sonyflake
Classifier: License :: OSI Approved :: BSD License
Classifier: Operating System :: POSIX :: Linux
Classifier: Programming Language :: Python :: 3
Classifier: Programming Language :: Python :: Implementation :: CPython
Classifier: Programming Language :: Python :: Free Threading :: 2 - Beta
Classifier: Intended Audience :: Developers
Requires-Python: >=3.8
License-File: LICENSE
Provides-Extra: dev
Requires-Dist: flake8 ; extra == 'dev'
Requires-Dist: flake8-pyproject ; extra == 'dev'
Requires-Dist: isort ; extra == 'dev'
Requires-Dist: mypy ; extra == 'dev'
Requires-Dist: pytest ; extra == 'dev'
